iproute/__init__.py
iproute-0.0.1.dist-info/LICENSE
iproute-0.0.1.dist-info/METADATA
iproute-0.0.1.dist-info/WHEEL
iproute-0.0.1.dist-info/top_level.txt
iproute-0.0.1.dist-info/RECORD
